{"version":1,"title":"INFO: task hung in lbs_remove_card","id":"091c62a620960f8f81cf089356da2db268d541d2","status":"upstream: reported C repro on 2025/08/14 09:42","first-crash":"2024-10-16T13:45:04.580686Z","last-crash":"2026-04-25T00:04:29.197813Z","discussions":["https://groups.google.com/d/msgid/syzkaller-bugs/689daf88.050a0220.2d37a5.0001.GAE@google.com"],"crashes":[{"title":"INFO: task hung in lbs_remove_card","syz-reproducer":"/text?tag=ReproSyz\u0026x=17ed8a02580000","c-reproducer":"/text?tag=ReproC\u0026x=121808ba580000","repro-opts":"{\"threaded\":true,\"repeat\":true,\"procs\":1,\"slowdown\":1,\"sandbox\":\"\",\"sandbox_arg\":0,\"close_fds\":false,\"callcomments\":true}","kernel-config":"/text?tag=KernelConfig\u0026x=f1500201919951cc","kernel-source-git":"https://git.kernel.org/pub/scm/linux/kernel/git/gregkh/usb.git","kernel-source-commit":"bb375c251ab40bdbc5272008fcf2bc6cd5266610","syzkaller-git":"https://github.com/google/syzkaller/commits/a9fe5c9ea5a79ea37834f2c5be830d0385f20199","syzkaller-commit":"a9fe5c9ea5a79ea37834f2c5be830d0385f20199","crash-report-link":"/text?tag=CrashReport\u0026x=162297e6580000"},{"title":"INFO: task hung in lbs_remove_card","syz-reproducer":"/text?tag=ReproSyz\u0026x=147398d6580000","c-reproducer":"/text?tag=ReproC\u0026x=11458a02580000","repro-opts":"{\"repeat\":true,\"procs\":1,\"slowdown\":1,\"sandbox\":\"\",\"sandbox_arg\":0,\"close_fds\":false,\"callcomments\":true}","kernel-config":"/text?tag=KernelConfig\u0026x=f1500201919951cc","kernel-source-git":"https://git.kernel.org/pub/scm/linux/kernel/git/gregkh/usb.git","kernel-source-commit":"bb375c251ab40bdbc5272008fcf2bc6cd5266610","syzkaller-git":"https://github.com/google/syzkaller/commits/a9fe5c9ea5a79ea37834f2c5be830d0385f20199","syzkaller-commit":"a9fe5c9ea5a79ea37834f2c5be830d0385f20199","crash-report-link":"/text?tag=CrashReport\u0026x=16b99b5a580000"},{"title":"INFO: task hung in lbs_remove_card","syz-reproducer":"/text?tag=ReproSyz\u0026x=157fe552580000","c-reproducer":"/text?tag=ReproC\u0026x=14952b5a580000","repro-opts":"{\"repeat\":true,\"procs\":1,\"slowdown\":1,\"sandbox\":\"\",\"sandbox_arg\":0,\"close_fds\":false,\"callcomments\":true}","kernel-config":"/text?tag=KernelConfig\u0026x=f1500201919951cc","kernel-source-git":"https://git.kernel.org/pub/scm/linux/kernel/git/gregkh/usb.git","kernel-source-commit":"bb375c251ab40bdbc5272008fcf2bc6cd5266610","syzkaller-git":"https://github.com/google/syzkaller/commits/a9fe5c9ea5a79ea37834f2c5be830d0385f20199","syzkaller-commit":"a9fe5c9ea5a79ea37834f2c5be830d0385f20199","crash-report-link":"/text?tag=CrashReport\u0026x=16d67b5a580000"},{"title":"INFO: task hung in lbs_remove_card","syz-reproducer":"/text?tag=ReproSyz\u0026x=1191555a580000","c-reproducer":"/text?tag=ReproC\u0026x=114a15c6580000","repro-opts":"{\"repeat\":true,\"procs\":1,\"slowdown\":1,\"sandbox\":\"\",\"sandbox_arg\":0,\"close_fds\":false,\"callcomments\":true}","kernel-config":"/text?tag=KernelConfig\u0026x=f1500201919951cc","kernel-source-git":"https://git.kernel.org/pub/scm/linux/kernel/git/gregkh/usb.git","kernel-source-commit":"bb375c251ab40bdbc5272008fcf2bc6cd5266610","syzkaller-git":"https://github.com/google/syzkaller/commits/a2f13f719e073f5891395e8e7374ba6640614a66","syzkaller-commit":"a2f13f719e073f5891395e8e7374ba6640614a66","crash-report-link":"/text?tag=CrashReport\u0026x=1775c24a580000"},{"title":"INFO: task hung in lbs_remove_card","kernel-config":"/text?tag=KernelConfig\u0026x=37c3a614a8bc8d27","kernel-source-git":"https://git.kernel.org/pub/scm/linux/kernel/git/gregkh/usb.git","kernel-source-commit":"2e68039281932e6dc37718a1ea7cbb8e2cda42e6","syzkaller-git":"https://github.com/google/syzkaller/commits/1c2b929100f5465bbe3bebeba1caf612ec1631a0","syzkaller-commit":"1c2b929100f5465bbe3bebeba1caf612ec1631a0","crash-report-link":"/text?tag=CrashReport\u0026x=14a0f702580000"},{"title":"INFO: task hung in lbs_remove_card","kernel-config":"/text?tag=KernelConfig\u0026x=37c3a614a8bc8d27","kernel-source-git":"https://git.kernel.org/pub/scm/linux/kernel/git/gregkh/usb.git","kernel-source-commit":"2e68039281932e6dc37718a1ea7cbb8e2cda42e6","syzkaller-git":"https://github.com/google/syzkaller/commits/1c2b929100f5465bbe3bebeba1caf612ec1631a0","syzkaller-commit":"1c2b929100f5465bbe3bebeba1caf612ec1631a0","crash-report-link":"/text?tag=CrashReport\u0026x=103fc2ce580000"},{"title":"INFO: task hung in lbs_remove_card","kernel-config":"/text?tag=KernelConfig\u0026x=37c3a614a8bc8d27","kernel-source-git":"https://git.kernel.org/pub/scm/linux/kernel/git/gregkh/usb.git","kernel-source-commit":"2e68039281932e6dc37718a1ea7cbb8e2cda42e6","syzkaller-git":"https://github.com/google/syzkaller/commits/1c2b929100f5465bbe3bebeba1caf612ec1631a0","syzkaller-commit":"1c2b929100f5465bbe3bebeba1caf612ec1631a0","crash-report-link":"/text?tag=CrashReport\u0026x=17f7c2ce580000"},{"title":"INFO: task hung in lbs_remove_card","kernel-config":"/text?tag=KernelConfig\u0026x=37c3a614a8bc8d27","kernel-source-git":"https://git.kernel.org/pub/scm/linux/kernel/git/gregkh/usb.git","kernel-source-commit":"2e68039281932e6dc37718a1ea7cbb8e2cda42e6","syzkaller-git":"https://github.com/google/syzkaller/commits/1c2b929100f5465bbe3bebeba1caf612ec1631a0","syzkaller-commit":"1c2b929100f5465bbe3bebeba1caf612ec1631a0","crash-report-link":"/text?tag=CrashReport\u0026x=12877702580000"},{"title":"INFO: task hung in lbs_remove_card","kernel-config":"/text?tag=KernelConfig\u0026x=37c3a614a8bc8d27","kernel-source-git":"https://git.kernel.org/pub/scm/linux/kernel/git/gregkh/usb.git","kernel-source-commit":"2e68039281932e6dc37718a1ea7cbb8e2cda42e6","syzkaller-git":"https://github.com/google/syzkaller/commits/1c2b929100f5465bbe3bebeba1caf612ec1631a0","syzkaller-commit":"1c2b929100f5465bbe3bebeba1caf612ec1631a0","crash-report-link":"/text?tag=CrashReport\u0026x=114ae2ce580000"},{"title":"INFO: task hung in lbs_remove_card","kernel-config":"/text?tag=KernelConfig\u0026x=37c3a614a8bc8d27","kernel-source-git":"https://git.kernel.org/pub/scm/linux/kernel/git/gregkh/usb.git","kernel-source-commit":"2e68039281932e6dc37718a1ea7cbb8e2cda42e6","syzkaller-git":"https://github.com/google/syzkaller/commits/1c2b929100f5465bbe3bebeba1caf612ec1631a0","syzkaller-commit":"1c2b929100f5465bbe3bebeba1caf612ec1631a0","crash-report-link":"/text?tag=CrashReport\u0026x=1563c2ce580000"},{"title":"INFO: task hung in lbs_remove_card","kernel-config":"/text?tag=KernelConfig\u0026x=37c3a614a8bc8d27","kernel-source-git":"https://git.kernel.org/pub/scm/linux/kernel/git/gregkh/usb.git","kernel-source-commit":"2e68039281932e6dc37718a1ea7cbb8e2cda42e6","syzkaller-git":"https://github.com/google/syzkaller/commits/1c2b929100f5465bbe3bebeba1caf612ec1631a0","syzkaller-commit":"1c2b929100f5465bbe3bebeba1caf612ec1631a0","crash-report-link":"/text?tag=CrashReport\u0026x=11bcfcce580000"},{"title":"INFO: task hung in lbs_remove_card","kernel-config":"/text?tag=KernelConfig\u0026x=37c3a614a8bc8d27","kernel-source-git":"https://git.kernel.org/pub/scm/linux/kernel/git/gregkh/usb.git","kernel-source-commit":"2e68039281932e6dc37718a1ea7cbb8e2cda42e6","syzkaller-git":"https://github.com/google/syzkaller/commits/1c2b929100f5465bbe3bebeba1caf612ec1631a0","syzkaller-commit":"1c2b929100f5465bbe3bebeba1caf612ec1631a0","crash-report-link":"/text?tag=CrashReport\u0026x=12d7ec36580000"},{"title":"INFO: task hung in lbs_remove_card","kernel-config":"/text?tag=KernelConfig\u0026x=37c3a614a8bc8d27","kernel-source-git":"https://git.kernel.org/pub/scm/linux/kernel/git/gregkh/usb.git","kernel-source-commit":"2e68039281932e6dc37718a1ea7cbb8e2cda42e6","syzkaller-git":"https://github.com/google/syzkaller/commits/1c2b929100f5465bbe3bebeba1caf612ec1631a0","syzkaller-commit":"1c2b929100f5465bbe3bebeba1caf612ec1631a0","crash-report-link":"/text?tag=CrashReport\u0026x=13bbec36580000"},{"title":"INFO: task hung in lbs_remove_card","kernel-config":"/text?tag=KernelConfig\u0026x=37c3a614a8bc8d27","kernel-source-git":"https://git.kernel.org/pub/scm/linux/kernel/git/gregkh/usb.git","kernel-source-commit":"2e68039281932e6dc37718a1ea7cbb8e2cda42e6","syzkaller-git":"https://github.com/google/syzkaller/commits/1c2b929100f5465bbe3bebeba1caf612ec1631a0","syzkaller-commit":"1c2b929100f5465bbe3bebeba1caf612ec1631a0","crash-report-link":"/text?tag=CrashReport\u0026x=16b97702580000"},{"title":"INFO: task hung in lbs_remove_card","kernel-config":"/text?tag=KernelConfig\u0026x=37c3a614a8bc8d27","kernel-source-git":"https://git.kernel.org/pub/scm/linux/kernel/git/gregkh/usb.git","kernel-source-commit":"2e68039281932e6dc37718a1ea7cbb8e2cda42e6","syzkaller-git":"https://github.com/google/syzkaller/commits/1c2b929100f5465bbe3bebeba1caf612ec1631a0","syzkaller-commit":"1c2b929100f5465bbe3bebeba1caf612ec1631a0","crash-report-link":"/text?tag=CrashReport\u0026x=175a1cce580000"},{"title":"INFO: task hung in lbs_remove_card","kernel-config":"/text?tag=KernelConfig\u0026x=37c3a614a8bc8d27","kernel-source-git":"https://git.kernel.org/pub/scm/linux/kernel/git/gregkh/usb.git","kernel-source-commit":"2e68039281932e6dc37718a1ea7cbb8e2cda42e6","syzkaller-git":"https://github.com/google/syzkaller/commits/1c2b929100f5465bbe3bebeba1caf612ec1631a0","syzkaller-commit":"1c2b929100f5465bbe3bebeba1caf612ec1631a0","crash-report-link":"/text?tag=CrashReport\u0026x=175dec36580000"},{"title":"INFO: task hung in lbs_remove_card","kernel-config":"/text?tag=KernelConfig\u0026x=37c3a614a8bc8d27","kernel-source-git":"https://git.kernel.org/pub/scm/linux/kernel/git/gregkh/usb.git","kernel-source-commit":"2e68039281932e6dc37718a1ea7cbb8e2cda42e6","syzkaller-git":"https://github.com/google/syzkaller/commits/1c2b929100f5465bbe3bebeba1caf612ec1631a0","syzkaller-commit":"1c2b929100f5465bbe3bebeba1caf612ec1631a0","crash-report-link":"/text?tag=CrashReport\u0026x=13ae7702580000"},{"title":"INFO: task hung in lbs_remove_card","kernel-config":"/text?tag=KernelConfig\u0026x=37c3a614a8bc8d27","kernel-source-git":"https://git.kernel.org/pub/scm/linux/kernel/git/gregkh/usb.git","kernel-source-commit":"2e68039281932e6dc37718a1ea7cbb8e2cda42e6","syzkaller-git":"https://github.com/google/syzkaller/commits/1c2b929100f5465bbe3bebeba1caf612ec1631a0","syzkaller-commit":"1c2b929100f5465bbe3bebeba1caf612ec1631a0","crash-report-link":"/text?tag=CrashReport\u0026x=168692d2580000"},{"title":"INFO: task hung in lbs_remove_card","kernel-config":"/text?tag=KernelConfig\u0026x=37c3a614a8bc8d27","kernel-source-git":"https://git.kernel.org/pub/scm/linux/kernel/git/gregkh/usb.git","kernel-source-commit":"2e68039281932e6dc37718a1ea7cbb8e2cda42e6","syzkaller-git":"https://github.com/google/syzkaller/commits/9cfb3ca710b61b2f1e2032fa6d94d4a00f81ab36","syzkaller-commit":"9cfb3ca710b61b2f1e2032fa6d94d4a00f81ab36","crash-report-link":"/text?tag=CrashReport\u0026x=17541cce580000"},{"title":"INFO: task hung in lbs_remove_card","kernel-config":"/text?tag=KernelConfig\u0026x=37c3a614a8bc8d27","kernel-source-git":"https://git.kernel.org/pub/scm/linux/kernel/git/gregkh/usb.git","kernel-source-commit":"2e68039281932e6dc37718a1ea7cbb8e2cda42e6","syzkaller-git":"https://github.com/google/syzkaller/commits/9cfb3ca710b61b2f1e2032fa6d94d4a00f81ab36","syzkaller-commit":"9cfb3ca710b61b2f1e2032fa6d94d4a00f81ab36","crash-report-link":"/text?tag=CrashReport\u0026x=12781cce580000"},{"title":"INFO: task hung in lbs_remove_card","kernel-config":"/text?tag=KernelConfig\u0026x=37c3a614a8bc8d27","kernel-source-git":"https://git.kernel.org/pub/scm/linux/kernel/git/gregkh/usb.git","kernel-source-commit":"2e68039281932e6dc37718a1ea7cbb8e2cda42e6","syzkaller-git":"https://github.com/google/syzkaller/commits/9cfb3ca710b61b2f1e2032fa6d94d4a00f81ab36","syzkaller-commit":"9cfb3ca710b61b2f1e2032fa6d94d4a00f81ab36","crash-report-link":"/text?tag=CrashReport\u0026x=176a5e6a580000"},{"title":"INFO: task hung in lbs_remove_card","kernel-config":"/text?tag=KernelConfig\u0026x=37c3a614a8bc8d27","kernel-source-git":"https://git.kernel.org/pub/scm/linux/kernel/git/gregkh/usb.git","kernel-source-commit":"2e68039281932e6dc37718a1ea7cbb8e2cda42e6","syzkaller-git":"https://github.com/google/syzkaller/commits/9cfb3ca710b61b2f1e2032fa6d94d4a00f81ab36","syzkaller-commit":"9cfb3ca710b61b2f1e2032fa6d94d4a00f81ab36","crash-report-link":"/text?tag=CrashReport\u0026x=16abb1ba580000"},{"title":"INFO: task hung in lbs_remove_card","kernel-config":"/text?tag=KernelConfig\u0026x=37c3a614a8bc8d27","kernel-source-git":"https://git.kernel.org/pub/scm/linux/kernel/git/gregkh/usb.git","kernel-source-commit":"2e68039281932e6dc37718a1ea7cbb8e2cda42e6","syzkaller-git":"https://github.com/google/syzkaller/commits/9cfb3ca710b61b2f1e2032fa6d94d4a00f81ab36","syzkaller-commit":"9cfb3ca710b61b2f1e2032fa6d94d4a00f81ab36","crash-report-link":"/text?tag=CrashReport\u0026x=169eec36580000"},{"title":"INFO: task hung in lbs_remove_card","kernel-config":"/text?tag=KernelConfig\u0026x=37c3a614a8bc8d27","kernel-source-git":"https://git.kernel.org/pub/scm/linux/kernel/git/gregkh/usb.git","kernel-source-commit":"2e68039281932e6dc37718a1ea7cbb8e2cda42e6","syzkaller-git":"https://github.com/google/syzkaller/commits/9cfb3ca710b61b2f1e2032fa6d94d4a00f81ab36","syzkaller-commit":"9cfb3ca710b61b2f1e2032fa6d94d4a00f81ab36","crash-report-link":"/text?tag=CrashReport\u0026x=11d5b1ba580000"},{"title":"INFO: task hung in lbs_remove_card","kernel-config":"/text?tag=KernelConfig\u0026x=37c3a614a8bc8d27","kernel-source-git":"https://git.kernel.org/pub/scm/linux/kernel/git/gregkh/usb.git","kernel-source-commit":"2e68039281932e6dc37718a1ea7cbb8e2cda42e6","syzkaller-git":"https://github.com/google/syzkaller/commits/9cfb3ca710b61b2f1e2032fa6d94d4a00f81ab36","syzkaller-commit":"9cfb3ca710b61b2f1e2032fa6d94d4a00f81ab36","crash-report-link":"/text?tag=CrashReport\u0026x=1773ecce580000"},{"title":"INFO: task hung in lbs_remove_card","kernel-config":"/text?tag=KernelConfig\u0026x=37c3a614a8bc8d27","kernel-source-git":"https://git.kernel.org/pub/scm/linux/kernel/git/gregkh/usb.git","kernel-source-commit":"2e68039281932e6dc37718a1ea7cbb8e2cda42e6","syzkaller-git":"https://github.com/google/syzkaller/commits/9cfb3ca710b61b2f1e2032fa6d94d4a00f81ab36","syzkaller-commit":"9cfb3ca710b61b2f1e2032fa6d94d4a00f81ab36","crash-report-link":"/text?tag=CrashReport\u0026x=14857cce580000"},{"title":"INFO: task hung in lbs_remove_card","kernel-config":"/text?tag=KernelConfig\u0026x=37c3a614a8bc8d27","kernel-source-git":"https://git.kernel.org/pub/scm/linux/kernel/git/gregkh/usb.git","kernel-source-commit":"2e68039281932e6dc37718a1ea7cbb8e2cda42e6","syzkaller-git":"https://github.com/google/syzkaller/commits/9cfb3ca710b61b2f1e2032fa6d94d4a00f81ab36","syzkaller-commit":"9cfb3ca710b61b2f1e2032fa6d94d4a00f81ab36","crash-report-link":"/text?tag=CrashReport\u0026x=147fb702580000"},{"title":"INFO: task hung in lbs_remove_card","kernel-config":"/text?tag=KernelConfig\u0026x=37c3a614a8bc8d27","kernel-source-git":"https://git.kernel.org/pub/scm/linux/kernel/git/gregkh/usb.git","kernel-source-commit":"2e68039281932e6dc37718a1ea7cbb8e2cda42e6","syzkaller-git":"https://github.com/google/syzkaller/commits/9cfb3ca710b61b2f1e2032fa6d94d4a00f81ab36","syzkaller-commit":"9cfb3ca710b61b2f1e2032fa6d94d4a00f81ab36","crash-report-link":"/text?tag=CrashReport\u0026x=120f12d2580000"},{"title":"INFO: task hung in lbs_remove_card","kernel-config":"/text?tag=KernelConfig\u0026x=37c3a614a8bc8d27","kernel-source-git":"https://git.kernel.org/pub/scm/linux/kernel/git/gregkh/usb.git","kernel-source-commit":"2e68039281932e6dc37718a1ea7cbb8e2cda42e6","syzkaller-git":"https://github.com/google/syzkaller/commits/9cfb3ca710b61b2f1e2032fa6d94d4a00f81ab36","syzkaller-commit":"9cfb3ca710b61b2f1e2032fa6d94d4a00f81ab36","crash-report-link":"/text?tag=CrashReport\u0026x=137742ce580000"},{"title":"INFO: task hung in lbs_remove_card","kernel-config":"/text?tag=KernelConfig\u0026x=37c3a614a8bc8d27","kernel-source-git":"https://git.kernel.org/pub/scm/linux/kernel/git/gregkh/usb.git","kernel-source-commit":"2e68039281932e6dc37718a1ea7cbb8e2cda42e6","syzkaller-git":"https://github.com/google/syzkaller/commits/9cfb3ca710b61b2f1e2032fa6d94d4a00f81ab36","syzkaller-commit":"9cfb3ca710b61b2f1e2032fa6d94d4a00f81ab36","crash-report-link":"/text?tag=CrashReport\u0026x=154e7cce580000"},{"title":"INFO: task hung in lbs_remove_card","kernel-config":"/text?tag=KernelConfig\u0026x=37c3a614a8bc8d27","kernel-source-git":"https://git.kernel.org/pub/scm/linux/kernel/git/gregkh/usb.git","kernel-source-commit":"2e68039281932e6dc37718a1ea7cbb8e2cda42e6","syzkaller-git":"https://github.com/google/syzkaller/commits/9cfb3ca710b61b2f1e2032fa6d94d4a00f81ab36","syzkaller-commit":"9cfb3ca710b61b2f1e2032fa6d94d4a00f81ab36","crash-report-link":"/text?tag=CrashReport\u0026x=144742ce580000"},{"title":"INFO: task hung in lbs_remove_card","kernel-config":"/text?tag=KernelConfig\u0026x=37c3a614a8bc8d27","kernel-source-git":"https://git.kernel.org/pub/scm/linux/kernel/git/gregkh/usb.git","kernel-source-commit":"2e68039281932e6dc37718a1ea7cbb8e2cda42e6","syzkaller-git":"https://github.com/google/syzkaller/commits/4c3406dcb7532a40c27b01ca073cca0025fefd2c","syzkaller-commit":"4c3406dcb7532a40c27b01ca073cca0025fefd2c","crash-report-link":"/text?tag=CrashReport\u0026x=1662b1ba580000"},{"title":"INFO: task hung in lbs_remove_card","kernel-config":"/text?tag=KernelConfig\u0026x=37c3a614a8bc8d27","kernel-source-git":"https://git.kernel.org/pub/scm/linux/kernel/git/gregkh/usb.git","kernel-source-commit":"2e68039281932e6dc37718a1ea7cbb8e2cda42e6","syzkaller-git":"https://github.com/google/syzkaller/commits/4c3406dcb7532a40c27b01ca073cca0025fefd2c","syzkaller-commit":"4c3406dcb7532a40c27b01ca073cca0025fefd2c","crash-report-link":"/text?tag=CrashReport\u0026x=1321ecce580000"},{"title":"INFO: task hung in lbs_remove_card","kernel-config":"/text?tag=KernelConfig\u0026x=37c3a614a8bc8d27","kernel-source-git":"https://git.kernel.org/pub/scm/linux/kernel/git/gregkh/usb.git","kernel-source-commit":"2e68039281932e6dc37718a1ea7cbb8e2cda42e6","syzkaller-git":"https://github.com/google/syzkaller/commits/4c3406dcb7532a40c27b01ca073cca0025fefd2c","syzkaller-commit":"4c3406dcb7532a40c27b01ca073cca0025fefd2c","crash-report-link":"/text?tag=CrashReport\u0026x=16727cce580000"},{"title":"INFO: task hung in lbs_remove_card","kernel-config":"/text?tag=KernelConfig\u0026x=37c3a614a8bc8d27","kernel-source-git":"https://git.kernel.org/pub/scm/linux/kernel/git/gregkh/usb.git","kernel-source-commit":"2e68039281932e6dc37718a1ea7cbb8e2cda42e6","syzkaller-git":"https://github.com/google/syzkaller/commits/4c3406dcb7532a40c27b01ca073cca0025fefd2c","syzkaller-commit":"4c3406dcb7532a40c27b01ca073cca0025fefd2c","crash-report-link":"/text?tag=CrashReport\u0026x=11b8b1ba580000"},{"title":"INFO: task hung in lbs_remove_card","kernel-config":"/text?tag=KernelConfig\u0026x=37c3a614a8bc8d27","kernel-source-git":"https://git.kernel.org/pub/scm/linux/kernel/git/gregkh/usb.git","kernel-source-commit":"2e68039281932e6dc37718a1ea7cbb8e2cda42e6","syzkaller-git":"https://github.com/google/syzkaller/commits/4c3406dcb7532a40c27b01ca073cca0025fefd2c","syzkaller-commit":"4c3406dcb7532a40c27b01ca073cca0025fefd2c","crash-report-link":"/text?tag=CrashReport\u0026x=16000096580000"},{"title":"INFO: task hung in lbs_remove_card","kernel-config":"/text?tag=KernelConfig\u0026x=37c3a614a8bc8d27","kernel-source-git":"https://git.kernel.org/pub/scm/linux/kernel/git/gregkh/usb.git","kernel-source-commit":"2e68039281932e6dc37718a1ea7cbb8e2cda42e6","syzkaller-git":"https://github.com/google/syzkaller/commits/4c3406dcb7532a40c27b01ca073cca0025fefd2c","syzkaller-commit":"4c3406dcb7532a40c27b01ca073cca0025fefd2c","crash-report-link":"/text?tag=CrashReport\u0026x=15247cce580000"},{"title":"INFO: task hung in lbs_remove_card","kernel-config":"/text?tag=KernelConfig\u0026x=37c3a614a8bc8d27","kernel-source-git":"https://git.kernel.org/pub/scm/linux/kernel/git/gregkh/usb.git","kernel-source-commit":"2e68039281932e6dc37718a1ea7cbb8e2cda42e6","syzkaller-git":"https://github.com/google/syzkaller/commits/4c3406dcb7532a40c27b01ca073cca0025fefd2c","syzkaller-commit":"4c3406dcb7532a40c27b01ca073cca0025fefd2c","crash-report-link":"/text?tag=CrashReport\u0026x=17feb702580000"},{"title":"INFO: task hung in lbs_remove_card","kernel-config":"/text?tag=KernelConfig\u0026x=37c3a614a8bc8d27","kernel-source-git":"https://git.kernel.org/pub/scm/linux/kernel/git/gregkh/usb.git","kernel-source-commit":"2e68039281932e6dc37718a1ea7cbb8e2cda42e6","syzkaller-git":"https://github.com/google/syzkaller/commits/4c3406dcb7532a40c27b01ca073cca0025fefd2c","syzkaller-commit":"4c3406dcb7532a40c27b01ca073cca0025fefd2c","crash-report-link":"/text?tag=CrashReport\u0026x=145eb702580000"},{"title":"INFO: task hung in lbs_remove_card","kernel-config":"/text?tag=KernelConfig\u0026x=37c3a614a8bc8d27","kernel-source-git":"https://git.kernel.org/pub/scm/linux/kernel/git/gregkh/usb.git","kernel-source-commit":"2e68039281932e6dc37718a1ea7cbb8e2cda42e6","syzkaller-git":"https://github.com/google/syzkaller/commits/4c3406dcb7532a40c27b01ca073cca0025fefd2c","syzkaller-commit":"4c3406dcb7532a40c27b01ca073cca0025fefd2c","crash-report-link":"/text?tag=CrashReport\u0026x=16a36c36580000"},{"title":"INFO: task hung in lbs_remove_card","kernel-config":"/text?tag=KernelConfig\u0026x=37c3a614a8bc8d27","kernel-source-git":"https://git.kernel.org/pub/scm/linux/kernel/git/gregkh/usb.git","kernel-source-commit":"2e68039281932e6dc37718a1ea7cbb8e2cda42e6","syzkaller-git":"https://github.com/google/syzkaller/commits/4c3406dcb7532a40c27b01ca073cca0025fefd2c","syzkaller-commit":"4c3406dcb7532a40c27b01ca073cca0025fefd2c","crash-report-link":"/text?tag=CrashReport\u0026x=113331ba580000"},{"title":"INFO: task hung in lbs_remove_card","kernel-config":"/text?tag=KernelConfig\u0026x=37c3a614a8bc8d27","kernel-source-git":"https://git.kernel.org/pub/scm/linux/kernel/git/gregkh/usb.git","kernel-source-commit":"2e68039281932e6dc37718a1ea7cbb8e2cda42e6","syzkaller-git":"https://github.com/google/syzkaller/commits/4c3406dcb7532a40c27b01ca073cca0025fefd2c","syzkaller-commit":"4c3406dcb7532a40c27b01ca073cca0025fefd2c","crash-report-link":"/text?tag=CrashReport\u0026x=178e42ce580000"},{"title":"INFO: task hung in lbs_remove_card","kernel-config":"/text?tag=KernelConfig\u0026x=37c3a614a8bc8d27","kernel-source-git":"https://git.kernel.org/pub/scm/linux/kernel/git/gregkh/usb.git","kernel-source-commit":"2e68039281932e6dc37718a1ea7cbb8e2cda42e6","syzkaller-git":"https://github.com/google/syzkaller/commits/4c3406dcb7532a40c27b01ca073cca0025fefd2c","syzkaller-commit":"4c3406dcb7532a40c27b01ca073cca0025fefd2c","crash-report-link":"/text?tag=CrashReport\u0026x=17e9ae6a580000"},{"title":"INFO: task hung in lbs_remove_card","kernel-config":"/text?tag=KernelConfig\u0026x=37c3a614a8bc8d27","kernel-source-git":"https://git.kernel.org/pub/scm/linux/kernel/git/gregkh/usb.git","kernel-source-commit":"2e68039281932e6dc37718a1ea7cbb8e2cda42e6","syzkaller-git":"https://github.com/google/syzkaller/commits/4c3406dcb7532a40c27b01ca073cca0025fefd2c","syzkaller-commit":"4c3406dcb7532a40c27b01ca073cca0025fefd2c","crash-report-link":"/text?tag=CrashReport\u0026x=13aa12d2580000"},{"title":"INFO: task hung in lbs_remove_card","kernel-config":"/text?tag=KernelConfig\u0026x=37c3a614a8bc8d27","kernel-source-git":"https://git.kernel.org/pub/scm/linux/kernel/git/gregkh/usb.git","kernel-source-commit":"2e68039281932e6dc37718a1ea7cbb8e2cda42e6","syzkaller-git":"https://github.com/google/syzkaller/commits/4c3406dcb7532a40c27b01ca073cca0025fefd2c","syzkaller-commit":"4c3406dcb7532a40c27b01ca073cca0025fefd2c","crash-report-link":"/text?tag=CrashReport\u0026x=103531ba580000"},{"title":"INFO: task hung in lbs_remove_card","kernel-config":"/text?tag=KernelConfig\u0026x=37c3a614a8bc8d27","kernel-source-git":"https://git.kernel.org/pub/scm/linux/kernel/git/gregkh/usb.git","kernel-source-commit":"2e68039281932e6dc37718a1ea7cbb8e2cda42e6","syzkaller-git":"https://github.com/google/syzkaller/commits/b10da5ec66a755e57e73801e716c78a16443611f","syzkaller-commit":"b10da5ec66a755e57e73801e716c78a16443611f","crash-report-link":"/text?tag=CrashReport\u0026x=152f6cce580000"},{"title":"INFO: task hung in lbs_remove_card","kernel-config":"/text?tag=KernelConfig\u0026x=fc65f9fdda222232","kernel-source-git":"https://git.kernel.org/pub/scm/linux/kernel/git/gregkh/usb.git","kernel-source-commit":"2b38afce25c4e1b8f943ff4f0a2b51d6c40f2ed2","syzkaller-git":"https://github.com/google/syzkaller/commits/c06e8995d711b5a8d8fbd771826fcbfdac6f110f","syzkaller-commit":"c06e8995d711b5a8d8fbd771826fcbfdac6f110f","crash-report-link":"/text?tag=CrashReport\u0026x=16f419a2580000"},{"title":"INFO: task hung in lbs_remove_card","kernel-config":"/text?tag=KernelConfig\u0026x=fc65f9fdda222232","kernel-source-git":"https://git.kernel.org/pub/scm/linux/kernel/git/gregkh/usb.git","kernel-source-commit":"c30a13538d9f8b2a60b2f6b26abe046dea10aa12","syzkaller-git":"https://github.com/google/syzkaller/commits/32a0e5edfeef60e894c453dc9e9ae45528626ef1","syzkaller-commit":"32a0e5edfeef60e894c453dc9e9ae45528626ef1","crash-report-link":"/text?tag=CrashReport\u0026x=15033434580000"},{"title":"INFO: task hung in lbs_remove_card","kernel-config":"/text?tag=KernelConfig\u0026x=6f764ce607e41bad","kernel-source-git":"https://git.kernel.org/pub/scm/linux/kernel/git/gregkh/usb.git","kernel-source-commit":"d632ab86aff2cef21f794e337a8e7f2320ac3973","syzkaller-git":"https://github.com/google/syzkaller/commits/37880f406e705722b43905dc07379a234a14f86d","syzkaller-commit":"37880f406e705722b43905dc07379a234a14f86d","crash-report-link":"/text?tag=CrashReport\u0026x=1191a042580000"}]}