{"version":1,"title":"inconsistent lock state in bpf_lru_push_free","id":"c4d6f5f7d392471722983a2e85ae391360ca7ae8","status":"upstream: reported C repro on 2025/12/22 19:02","first-crash":"2025-12-22T18:11:46.211404Z","last-crash":"2026-04-02T10:35:20.766676Z","discussions":["https://groups.google.com/d/msgid/syzkaller-bugs/694995bf.050a0220.2fb209.01a1.GAE@google.com"],"crashes":[{"title":"inconsistent lock state in bpf_lru_push_free","syz-reproducer":"/text?tag=ReproSyz\u0026x=10ec92fc580000","c-reproducer":"/text?tag=ReproC\u0026x=15f32422580000","kernel-config":"/text?tag=KernelConfig\u0026x=a94030c847137a18","kernel-source-git":"git://git.kernel.org/pub/scm/linux/kernel/git/bpf/bpf.git","kernel-source-commit":"22cc16c04b7893d8fc22810599f49a305d600b9e","syzkaller-git":"https://github.com/google/syzkaller/commits/d6526ea3e6ad9081c902859bbb80f9f840377cb4","syzkaller-commit":"d6526ea3e6ad9081c902859bbb80f9f840377cb4","crash-report-link":"/text?tag=CrashReport\u0026x=11cef49a580000"},{"title":"inconsistent lock state in bpf_lru_push_free","syz-reproducer":"/text?tag=ReproSyz\u0026x=16f4649a580000","c-reproducer":"/text?tag=ReproC\u0026x=114f5bb4580000","kernel-config":"/text?tag=KernelConfig\u0026x=a94030c847137a18","kernel-source-git":"git://git.kernel.org/pub/scm/linux/kernel/git/bpf/bpf.git","kernel-source-commit":"22cc16c04b7893d8fc22810599f49a305d600b9e","syzkaller-git":"https://github.com/google/syzkaller/commits/d6526ea3e6ad9081c902859bbb80f9f840377cb4","syzkaller-commit":"d6526ea3e6ad9081c902859bbb80f9f840377cb4","crash-report-link":"/text?tag=CrashReport\u0026x=17713022580000"},{"title":"inconsistent lock state in bpf_lru_push_free","syz-reproducer":"/text?tag=ReproSyz\u0026x=1466e89a580000","c-reproducer":"/text?tag=ReproC\u0026x=1147f09a580000","kernel-config":"/text?tag=KernelConfig\u0026x=a94030c847137a18","kernel-source-git":"git://git.kernel.org/pub/scm/linux/kernel/git/bpf/bpf.git","kernel-source-commit":"22cc16c04b7893d8fc22810599f49a305d600b9e","syzkaller-git":"https://github.com/google/syzkaller/commits/d6526ea3e6ad9081c902859bbb80f9f840377cb4","syzkaller-commit":"d6526ea3e6ad9081c902859bbb80f9f840377cb4","crash-report-link":"/text?tag=CrashReport\u0026x=1610c89a580000"},{"title":"inconsistent lock state in bpf_lru_push_free","syz-reproducer":"/text?tag=ReproSyz\u0026x=17eddf1a580000","c-reproducer":"/text?tag=ReproC\u0026x=15aaef1a580000","kernel-config":"/text?tag=KernelConfig\u0026x=a94030c847137a18","kernel-source-git":"git://git.kernel.org/pub/scm/linux/kernel/git/bpf/bpf.git","kernel-source-commit":"22cc16c04b7893d8fc22810599f49a305d600b9e","syzkaller-git":"https://github.com/google/syzkaller/commits/d6526ea3e6ad9081c902859bbb80f9f840377cb4","syzkaller-commit":"d6526ea3e6ad9081c902859bbb80f9f840377cb4","crash-report-link":"/text?tag=CrashReport\u0026x=11924b92580000"},{"title":"inconsistent lock state in bpf_lru_push_free","syz-reproducer":"/text?tag=ReproSyz\u0026x=10cf6f1a580000","c-reproducer":"/text?tag=ReproC\u0026x=15578b92580000","kernel-config":"/text?tag=KernelConfig\u0026x=a94030c847137a18","kernel-source-git":"git://git.kernel.org/pub/scm/linux/kernel/git/bpf/bpf.git","kernel-source-commit":"22cc16c04b7893d8fc22810599f49a305d600b9e","syzkaller-git":"https://github.com/google/syzkaller/commits/d6526ea3e6ad9081c902859bbb80f9f840377cb4","syzkaller-commit":"d6526ea3e6ad9081c902859bbb80f9f840377cb4","crash-report-link":"/text?tag=CrashReport\u0026x=11c78f1a580000"},{"title":"inconsistent lock state in bpf_lru_push_free","syz-reproducer":"/text?tag=ReproSyz\u0026x=1529cd84580000","c-reproducer":"/text?tag=ReproC\u0026x=10ac8f1a580000","kernel-config":"/text?tag=KernelConfig\u0026x=a94030c847137a18","kernel-source-git":"git://git.kernel.org/pub/scm/linux/kernel/git/bpf/bpf.git","kernel-source-commit":"22cc16c04b7893d8fc22810599f49a305d600b9e","syzkaller-git":"https://github.com/google/syzkaller/commits/d6526ea3e6ad9081c902859bbb80f9f840377cb4","syzkaller-commit":"d6526ea3e6ad9081c902859bbb80f9f840377cb4","crash-report-link":"/text?tag=CrashReport\u0026x=13bc8bb4580000"},{"title":"inconsistent lock state in bpf_lru_push_free","syz-reproducer":"/text?tag=ReproSyz\u0026x=1027af1a580000","c-reproducer":"/text?tag=ReproC\u0026x=103efb58580000","kernel-config":"/text?tag=KernelConfig\u0026x=a94030c847137a18","kernel-source-git":"git://git.kernel.org/pub/scm/linux/kernel/git/bpf/bpf.git","kernel-source-commit":"22cc16c04b7893d8fc22810599f49a305d600b9e","syzkaller-git":"https://github.com/google/syzkaller/commits/d6526ea3e6ad9081c902859bbb80f9f840377cb4","syzkaller-commit":"d6526ea3e6ad9081c902859bbb80f9f840377cb4","crash-report-link":"/text?tag=CrashReport\u0026x=17c7af1a580000"},{"title":"inconsistent lock state in bpf_lru_push_free","syz-reproducer":"/text?tag=ReproSyz\u0026x=123dafc2580000","c-reproducer":"/text?tag=ReproC\u0026x=15e5af1a580000","kernel-config":"/text?tag=KernelConfig\u0026x=a94030c847137a18","kernel-source-git":"git://git.kernel.org/pub/scm/linux/kernel/git/bpf/bpf.git","kernel-source-commit":"22cc16c04b7893d8fc22810599f49a305d600b9e","syzkaller-git":"https://github.com/google/syzkaller/commits/d6526ea3e6ad9081c902859bbb80f9f840377cb4","syzkaller-commit":"d6526ea3e6ad9081c902859bbb80f9f840377cb4","crash-report-link":"/text?tag=CrashReport\u0026x=117b5f7c580000"},{"title":"inconsistent lock state in bpf_lru_push_free","syz-reproducer":"/text?tag=ReproSyz\u0026x=14aaafc2580000","c-reproducer":"/text?tag=ReproC\u0026x=14660f1a580000","kernel-config":"/text?tag=KernelConfig\u0026x=a94030c847137a18","kernel-source-git":"git://git.kernel.org/pub/scm/linux/kernel/git/bpf/bpf.git","kernel-source-commit":"22cc16c04b7893d8fc22810599f49a305d600b9e","syzkaller-git":"https://github.com/google/syzkaller/commits/d6526ea3e6ad9081c902859bbb80f9f840377cb4","syzkaller-commit":"d6526ea3e6ad9081c902859bbb80f9f840377cb4","crash-report-link":"/text?tag=CrashReport\u0026x=153a0b92580000"},{"title":"inconsistent lock state in bpf_lru_push_free","syz-reproducer":"/text?tag=ReproSyz\u0026x=15920bb4580000","c-reproducer":"/text?tag=ReproC\u0026x=14d20f1a580000","kernel-config":"/text?tag=KernelConfig\u0026x=a94030c847137a18","kernel-source-git":"git://git.kernel.org/pub/scm/linux/kernel/git/bpf/bpf.git","kernel-source-commit":"22cc16c04b7893d8fc22810599f49a305d600b9e","syzkaller-git":"https://github.com/google/syzkaller/commits/d6526ea3e6ad9081c902859bbb80f9f840377cb4","syzkaller-commit":"d6526ea3e6ad9081c902859bbb80f9f840377cb4","crash-report-link":"/text?tag=CrashReport\u0026x=16020b92580000"},{"title":"inconsistent lock state in bpf_lru_push_free","syz-reproducer":"/text?tag=ReproSyz\u0026x=14b4808a580000","c-reproducer":"/text?tag=ReproC\u0026x=146c3db4580000","kernel-config":"/text?tag=KernelConfig\u0026x=a94030c847137a18","kernel-source-git":"git://git.kernel.org/pub/scm/linux/kernel/git/bpf/bpf.git","kernel-source-commit":"22cc16c04b7893d8fc22810599f49a305d600b9e","syzkaller-git":"https://github.com/google/syzkaller/commits/d6526ea3e6ad9081c902859bbb80f9f840377cb4","syzkaller-commit":"d6526ea3e6ad9081c902859bbb80f9f840377cb4","crash-report-link":"/text?tag=CrashReport\u0026x=16c34b1a580000"},{"title":"inconsistent lock state in bpf_lru_push_free","syz-reproducer":"/text?tag=ReproSyz\u0026x=10b0f7b4580000","c-reproducer":"/text?tag=ReproC\u0026x=1732a422580000","kernel-config":"/text?tag=KernelConfig\u0026x=a4aa52bacc0658d1","kernel-source-git":"git://git.kernel.org/pub/scm/linux/kernel/git/bpf/bpf-next.git","kernel-source-commit":"600605853f87a4b1c3530a63f78a3541633402b0","syzkaller-git":"https://github.com/google/syzkaller/commits/d6526ea3e6ad9081c902859bbb80f9f840377cb4","syzkaller-commit":"d6526ea3e6ad9081c902859bbb80f9f840377cb4","crash-report-link":"/text?tag=CrashReport\u0026x=1045429a580000"},{"title":"inconsistent lock state in bpf_lru_push_free","syz-reproducer":"/text?tag=ReproSyz\u0026x=1298029a580000","c-reproducer":"/text?tag=ReproC\u0026x=1698029a580000","kernel-config":"/text?tag=KernelConfig\u0026x=a4aa52bacc0658d1","kernel-source-git":"git://git.kernel.org/pub/scm/linux/kernel/git/bpf/bpf-next.git","kernel-source-commit":"f14cdb1367b947d373215e36cfe9c69768dbafc9","syzkaller-git":"https://github.com/google/syzkaller/commits/d6526ea3e6ad9081c902859bbb80f9f840377cb4","syzkaller-commit":"d6526ea3e6ad9081c902859bbb80f9f840377cb4","crash-report-link":"/text?tag=CrashReport\u0026x=15c1b49a580000"},{"title":"inconsistent lock state in bpf_lru_push_free","syz-reproducer":"/text?tag=ReproSyz\u0026x=1213eb92580000","c-reproducer":"/text?tag=ReproC\u0026x=1210c89a580000","kernel-config":"/text?tag=KernelConfig\u0026x=a4aa52bacc0658d1","kernel-source-git":"git://git.kernel.org/pub/scm/linux/kernel/git/bpf/bpf-next.git","kernel-source-commit":"f14cdb1367b947d373215e36cfe9c69768dbafc9","syzkaller-git":"https://github.com/google/syzkaller/commits/d6526ea3e6ad9081c902859bbb80f9f840377cb4","syzkaller-commit":"d6526ea3e6ad9081c902859bbb80f9f840377cb4","crash-report-link":"/text?tag=CrashReport\u0026x=119febb4580000"},{"title":"inconsistent lock state in bpf_lru_push_free","syz-reproducer":"/text?tag=ReproSyz\u0026x=16f9cd84580000","c-reproducer":"/text?tag=ReproC\u0026x=12fc8f1a580000","kernel-config":"/text?tag=KernelConfig\u0026x=a4aa52bacc0658d1","kernel-source-git":"git://git.kernel.org/pub/scm/linux/kernel/git/bpf/bpf-next.git","kernel-source-commit":"ac1c5bc7c4c7e20e2070e6eaa673fc3e11619dbb","syzkaller-git":"https://github.com/google/syzkaller/commits/d6526ea3e6ad9081c902859bbb80f9f840377cb4","syzkaller-commit":"d6526ea3e6ad9081c902859bbb80f9f840377cb4","crash-report-link":"/text?tag=CrashReport\u0026x=16128bb4580000"},{"title":"inconsistent lock state in bpf_lru_push_free","syz-reproducer":"/text?tag=ReproSyz\u0026x=10679f1a580000","c-reproducer":"/text?tag=ReproC\u0026x=11050b92580000","kernel-config":"/text?tag=KernelConfig\u0026x=a4aa52bacc0658d1","kernel-source-git":"git://git.kernel.org/pub/scm/linux/kernel/git/bpf/bpf-next.git","kernel-source-commit":"f785a31395d9cafb8b2c42c7358fad72a6463142","syzkaller-git":"https://github.com/google/syzkaller/commits/d6526ea3e6ad9081c902859bbb80f9f840377cb4","syzkaller-commit":"d6526ea3e6ad9081c902859bbb80f9f840377cb4","crash-report-link":"/text?tag=CrashReport\u0026x=12f1af1a580000"},{"title":"inconsistent lock state in bpf_lru_push_free","syz-reproducer":"/text?tag=ReproSyz\u0026x=1001afc2580000","c-reproducer":"/text?tag=ReproC\u0026x=15bdd71a580000","kernel-config":"/text?tag=KernelConfig\u0026x=a4aa52bacc0658d1","kernel-source-git":"git://git.kernel.org/pub/scm/linux/kernel/git/bpf/bpf-next.git","kernel-source-commit":"f785a31395d9cafb8b2c42c7358fad72a6463142","syzkaller-git":"https://github.com/google/syzkaller/commits/d6526ea3e6ad9081c902859bbb80f9f840377cb4","syzkaller-commit":"d6526ea3e6ad9081c902859bbb80f9f840377cb4","crash-report-link":"/text?tag=CrashReport\u0026x=11a55f7c580000"},{"title":"inconsistent lock state in bpf_lru_push_free","syz-reproducer":"/text?tag=ReproSyz\u0026x=17c34b1a580000","c-reproducer":"/text?tag=ReproC\u0026x=168d8b58580000","kernel-config":"/text?tag=KernelConfig\u0026x=a4aa52bacc0658d1","kernel-source-git":"git://git.kernel.org/pub/scm/linux/kernel/git/bpf/bpf-next.git","kernel-source-commit":"f785a31395d9cafb8b2c42c7358fad72a6463142","syzkaller-git":"https://github.com/google/syzkaller/commits/d6526ea3e6ad9081c902859bbb80f9f840377cb4","syzkaller-commit":"d6526ea3e6ad9081c902859bbb80f9f840377cb4","crash-report-link":"/text?tag=CrashReport\u0026x=116c3db4580000"},{"title":"inconsistent lock state in bpf_lru_push_free","syz-reproducer":"/text?tag=ReproSyz\u0026x=17458f1a580000","kernel-config":"/text?tag=KernelConfig\u0026x=a4aa52bacc0658d1","kernel-source-git":"git://git.kernel.org/pub/scm/linux/kernel/git/bpf/bpf-next.git","kernel-source-commit":"ac1c5bc7c4c7e20e2070e6eaa673fc3e11619dbb","syzkaller-git":"https://github.com/google/syzkaller/commits/d6526ea3e6ad9081c902859bbb80f9f840377cb4","syzkaller-commit":"d6526ea3e6ad9081c902859bbb80f9f840377cb4","crash-report-link":"/text?tag=CrashReport\u0026x=15156f1a580000"},{"title":"inconsistent lock state in bpf_lru_push_free","syz-reproducer":"/text?tag=ReproSyz\u0026x=17fe3b1a580000","kernel-config":"/text?tag=KernelConfig\u0026x=a4aa52bacc0658d1","kernel-source-git":"git://git.kernel.org/pub/scm/linux/kernel/git/bpf/bpf-next.git","kernel-source-commit":"f785a31395d9cafb8b2c42c7358fad72a6463142","syzkaller-git":"https://github.com/google/syzkaller/commits/d6526ea3e6ad9081c902859bbb80f9f840377cb4","syzkaller-commit":"d6526ea3e6ad9081c902859bbb80f9f840377cb4","crash-report-link":"/text?tag=CrashReport\u0026x=13fe3b1a580000"},{"title":"inconsistent lock state in bpf_lru_push_free","syz-reproducer":"/text?tag=ReproSyz\u0026x=1780f584580000","kernel-config":"/text?tag=KernelConfig\u0026x=a4aa52bacc0658d1","kernel-source-git":"git://git.kernel.org/pub/scm/linux/kernel/git/bpf/bpf-next.git","kernel-source-commit":"f785a31395d9cafb8b2c42c7358fad72a6463142","syzkaller-git":"https://github.com/google/syzkaller/commits/d6526ea3e6ad9081c902859bbb80f9f840377cb4","syzkaller-commit":"d6526ea3e6ad9081c902859bbb80f9f840377cb4","crash-report-link":"/text?tag=CrashReport\u0026x=17c98b58580000"},{"title":"inconsistent lock state in bpf_lru_push_free","kernel-config":"/text?tag=KernelConfig\u0026x=6754c86e8d9e4c91","kernel-source-git":"git://git.kernel.org/pub/scm/linux/kernel/git/bpf/bpf.git","kernel-source-commit":"ad8391d37f334ee73ba91926f8b4e4cf6d31ea04","syzkaller-git":"https://github.com/google/syzkaller/commits/0cb124d55f481a6632bf9d56812123fb40ea52c2","syzkaller-commit":"0cb124d55f481a6632bf9d56812123fb40ea52c2","crash-report-link":"/text?tag=CrashReport\u0026x=10160e06580000"},{"title":"inconsistent lock state in bpf_lru_push_free","kernel-config":"/text?tag=KernelConfig\u0026x=6754c86e8d9e4c91","kernel-source-git":"git://git.kernel.org/pub/scm/linux/kernel/git/bpf/bpf.git","kernel-source-commit":"e2d072d6a3d1369d289667f51cf771eefa3c0b26","syzkaller-git":"https://github.com/google/syzkaller/commits/0285fe54d874a019ff6a6aa2763776c251e073db","syzkaller-commit":"0285fe54d874a019ff6a6aa2763776c251e073db","crash-report-link":"/text?tag=CrashReport\u0026x=101afe26580000"},{"title":"inconsistent lock state in bpf_lru_push_free","kernel-config":"/text?tag=KernelConfig\u0026x=6754c86e8d9e4c91","kernel-source-git":"git://git.kernel.org/pub/scm/linux/kernel/git/bpf/bpf.git","kernel-source-commit":"e2d072d6a3d1369d289667f51cf771eefa3c0b26","syzkaller-git":"https://github.com/google/syzkaller/commits/0285fe54d874a019ff6a6aa2763776c251e073db","syzkaller-commit":"0285fe54d874a019ff6a6aa2763776c251e073db","crash-report-link":"/text?tag=CrashReport\u0026x=125754d2580000"},{"title":"inconsistent lock state in bpf_lru_push_free","kernel-config":"/text?tag=KernelConfig\u0026x=6754c86e8d9e4c91","kernel-source-git":"git://git.kernel.org/pub/scm/linux/kernel/git/bpf/bpf.git","kernel-source-commit":"c369299895a591d96745d6492d4888259b004a9e","syzkaller-git":"https://github.com/google/syzkaller/commits/d0af506ef4609d1bffbbbbae776b857a63d84b20","syzkaller-commit":"d0af506ef4609d1bffbbbbae776b857a63d84b20","crash-report-link":"/text?tag=CrashReport\u0026x=14c899f6580000"},{"title":"inconsistent lock state in bpf_lru_push_free","kernel-config":"/text?tag=KernelConfig\u0026x=6754c86e8d9e4c91","kernel-source-git":"git://git.kernel.org/pub/scm/linux/kernel/git/bpf/bpf.git","kernel-source-commit":"c369299895a591d96745d6492d4888259b004a9e","syzkaller-git":"https://github.com/google/syzkaller/commits/d0af506ef4609d1bffbbbbae776b857a63d84b20","syzkaller-commit":"d0af506ef4609d1bffbbbbae776b857a63d84b20","crash-report-link":"/text?tag=CrashReport\u0026x=102da1ca580000"},{"title":"inconsistent lock state in bpf_lru_push_free","kernel-config":"/text?tag=KernelConfig\u0026x=6754c86e8d9e4c91","kernel-source-git":"git://git.kernel.org/pub/scm/linux/kernel/git/bpf/bpf.git","kernel-source-commit":"c369299895a591d96745d6492d4888259b004a9e","syzkaller-git":"https://github.com/google/syzkaller/commits/458630d8a58d88d7c514fe99028b2f97b9348ed3","syzkaller-commit":"458630d8a58d88d7c514fe99028b2f97b9348ed3","crash-report-link":"/text?tag=CrashReport\u0026x=148eb3d6580000"},{"title":"inconsistent lock state in bpf_lru_push_free","kernel-config":"/text?tag=KernelConfig\u0026x=6754c86e8d9e4c91","kernel-source-git":"git://git.kernel.org/pub/scm/linux/kernel/git/bpf/bpf.git","kernel-source-commit":"c369299895a591d96745d6492d4888259b004a9e","syzkaller-git":"https://github.com/google/syzkaller/commits/458630d8a58d88d7c514fe99028b2f97b9348ed3","syzkaller-commit":"458630d8a58d88d7c514fe99028b2f97b9348ed3","crash-report-link":"/text?tag=CrashReport\u0026x=169a51ca580000"},{"title":"inconsistent lock state in bpf_lru_push_free","kernel-config":"/text?tag=KernelConfig\u0026x=6754c86e8d9e4c91","kernel-source-git":"git://git.kernel.org/pub/scm/linux/kernel/git/bpf/bpf.git","kernel-source-commit":"c369299895a591d96745d6492d4888259b004a9e","syzkaller-git":"https://github.com/google/syzkaller/commits/356bdfc961dd4d1eeb96ca7d9071058dc92d2dde","syzkaller-commit":"356bdfc961dd4d1eeb96ca7d9071058dc92d2dde","crash-report-link":"/text?tag=CrashReport\u0026x=13688116580000"},{"title":"inconsistent lock state in bpf_lru_push_free","kernel-config":"/text?tag=KernelConfig\u0026x=779072223d02a312","kernel-source-git":"git://git.kernel.org/pub/scm/linux/kernel/git/bpf/bpf.git","kernel-source-commit":"146bd2a87a65aa407bb17fac70d8d583d19aba06","syzkaller-git":"https://github.com/google/syzkaller/commits/5b92003d577daa0766edda7ed533d75e1ac545ff","syzkaller-commit":"5b92003d577daa0766edda7ed533d75e1ac545ff","crash-report-link":"/text?tag=CrashReport\u0026x=172a9e02580000"},{"title":"inconsistent lock state in bpf_lru_push_free","kernel-config":"/text?tag=KernelConfig\u0026x=779072223d02a312","kernel-source-git":"git://git.kernel.org/pub/scm/linux/kernel/git/bpf/bpf.git","kernel-source-commit":"146bd2a87a65aa407bb17fac70d8d583d19aba06","syzkaller-git":"https://github.com/google/syzkaller/commits/bd6dcb30873a835583692eaa69f3bafebcba1cfd","syzkaller-commit":"bd6dcb30873a835583692eaa69f3bafebcba1cfd","crash-report-link":"/text?tag=CrashReport\u0026x=1680f352580000"},{"title":"inconsistent lock state in bpf_lru_push_free","kernel-config":"/text?tag=KernelConfig\u0026x=779072223d02a312","kernel-source-git":"git://git.kernel.org/pub/scm/linux/kernel/git/bpf/bpf.git","kernel-source-commit":"e06e6b8001233241eb5b2e2791162f0585f50f4b","syzkaller-git":"https://github.com/google/syzkaller/commits/0199f9a13cef46cb5197b1be05347de27bd3bc10","syzkaller-commit":"0199f9a13cef46cb5197b1be05347de27bd3bc10","crash-report-link":"/text?tag=CrashReport\u0026x=131134ba580000"},{"title":"inconsistent lock state in bpf_lru_push_free","kernel-config":"/text?tag=KernelConfig\u0026x=779072223d02a312","kernel-source-git":"git://git.kernel.org/pub/scm/linux/kernel/git/bpf/bpf.git","kernel-source-commit":"e06e6b8001233241eb5b2e2791162f0585f50f4b","syzkaller-git":"https://github.com/google/syzkaller/commits/0199f9a13cef46cb5197b1be05347de27bd3bc10","syzkaller-commit":"0199f9a13cef46cb5197b1be05347de27bd3bc10","crash-report-link":"/text?tag=CrashReport\u0026x=1254cf4a580000"},{"title":"inconsistent lock state in bpf_lru_push_free","kernel-config":"/text?tag=KernelConfig\u0026x=779072223d02a312","kernel-source-git":"git://git.kernel.org/pub/scm/linux/kernel/git/bpf/bpf.git","kernel-source-commit":"e06e6b8001233241eb5b2e2791162f0585f50f4b","syzkaller-git":"https://github.com/google/syzkaller/commits/0737c18fd5018ea7240eb270c230c7078e83b9f5","syzkaller-commit":"0737c18fd5018ea7240eb270c230c7078e83b9f5","crash-report-link":"/text?tag=CrashReport\u0026x=17113d52580000"},{"title":"inconsistent lock state in bpf_lru_push_free","kernel-config":"/text?tag=KernelConfig\u0026x=779072223d02a312","kernel-source-git":"git://git.kernel.org/pub/scm/linux/kernel/git/bpf/bpf.git","kernel-source-commit":"e06e6b8001233241eb5b2e2791162f0585f50f4b","syzkaller-git":"https://github.com/google/syzkaller/commits/64e2142473e22b554eb1d3e389ed239b01aac46a","syzkaller-commit":"64e2142473e22b554eb1d3e389ed239b01aac46a","crash-report-link":"/text?tag=CrashReport\u0026x=12913406580000"},{"title":"inconsistent lock state in bpf_lru_push_free","kernel-config":"/text?tag=KernelConfig\u0026x=779072223d02a312","kernel-source-git":"git://git.kernel.org/pub/scm/linux/kernel/git/bpf/bpf.git","kernel-source-commit":"e06e6b8001233241eb5b2e2791162f0585f50f4b","syzkaller-git":"https://github.com/google/syzkaller/commits/ee8d34d6bd63c940254cb452fca7cb4fdfe419e8","syzkaller-commit":"ee8d34d6bd63c940254cb452fca7cb4fdfe419e8","crash-report-link":"/text?tag=CrashReport\u0026x=15d798ba580000"},{"title":"inconsistent lock state in bpf_lru_push_free","kernel-config":"/text?tag=KernelConfig\u0026x=779072223d02a312","kernel-source-git":"git://git.kernel.org/pub/scm/linux/kernel/git/bpf/bpf.git","kernel-source-commit":"e06e6b8001233241eb5b2e2791162f0585f50f4b","syzkaller-git":"https://github.com/google/syzkaller/commits/ee8d34d6bd63c940254cb452fca7cb4fdfe419e8","syzkaller-commit":"ee8d34d6bd63c940254cb452fca7cb4fdfe419e8","crash-report-link":"/text?tag=CrashReport\u0026x=13805602580000"},{"title":"inconsistent lock state in bpf_lru_push_free","kernel-config":"/text?tag=KernelConfig\u0026x=779072223d02a312","kernel-source-git":"git://git.kernel.org/pub/scm/linux/kernel/git/bpf/bpf.git","kernel-source-commit":"e06e6b8001233241eb5b2e2791162f0585f50f4b","syzkaller-git":"https://github.com/google/syzkaller/commits/ee8d34d6bd63c940254cb452fca7cb4fdfe419e8","syzkaller-commit":"ee8d34d6bd63c940254cb452fca7cb4fdfe419e8","crash-report-link":"/text?tag=CrashReport\u0026x=12639602580000"},{"title":"inconsistent lock state in bpf_lru_push_free","kernel-config":"/text?tag=KernelConfig\u0026x=779072223d02a312","kernel-source-git":"git://git.kernel.org/pub/scm/linux/kernel/git/bpf/bpf.git","kernel-source-commit":"e06e6b8001233241eb5b2e2791162f0585f50f4b","syzkaller-git":"https://github.com/google/syzkaller/commits/ee8d34d6bd63c940254cb452fca7cb4fdfe419e8","syzkaller-commit":"ee8d34d6bd63c940254cb452fca7cb4fdfe419e8","crash-report-link":"/text?tag=CrashReport\u0026x=12dadd52580000"},{"title":"inconsistent lock state in bpf_lru_push_free","kernel-config":"/text?tag=KernelConfig\u0026x=779072223d02a312","kernel-source-git":"git://git.kernel.org/pub/scm/linux/kernel/git/bpf/bpf.git","kernel-source-commit":"e06e6b8001233241eb5b2e2791162f0585f50f4b","syzkaller-git":"https://github.com/google/syzkaller/commits/ee8d34d6bd63c940254cb452fca7cb4fdfe419e8","syzkaller-commit":"ee8d34d6bd63c940254cb452fca7cb4fdfe419e8","crash-report-link":"/text?tag=CrashReport\u0026x=14d0a2d6580000"},{"title":"inconsistent lock state in bpf_lru_push_free","kernel-config":"/text?tag=KernelConfig\u0026x=779072223d02a312","kernel-source-git":"git://git.kernel.org/pub/scm/linux/kernel/git/bpf/bpf.git","kernel-source-commit":"e06e6b8001233241eb5b2e2791162f0585f50f4b","syzkaller-git":"https://github.com/google/syzkaller/commits/ee8d34d6bd63c940254cb452fca7cb4fdfe419e8","syzkaller-commit":"ee8d34d6bd63c940254cb452fca7cb4fdfe419e8","crash-report-link":"/text?tag=CrashReport\u0026x=1644d406580000"},{"title":"inconsistent lock state in bpf_lru_push_free","kernel-config":"/text?tag=KernelConfig\u0026x=779072223d02a312","kernel-source-git":"git://git.kernel.org/pub/scm/linux/kernel/git/bpf/bpf.git","kernel-source-commit":"e06e6b8001233241eb5b2e2791162f0585f50f4b","syzkaller-git":"https://github.com/google/syzkaller/commits/351cb5cf1aae9dba0fe20d76bd03ff67aaf96a2e","syzkaller-commit":"351cb5cf1aae9dba0fe20d76bd03ff67aaf96a2e","crash-report-link":"/text?tag=CrashReport\u0026x=13735406580000"},{"title":"inconsistent lock state in bpf_lru_push_free","kernel-config":"/text?tag=KernelConfig\u0026x=779072223d02a312","kernel-source-git":"git://git.kernel.org/pub/scm/linux/kernel/git/bpf/bpf.git","kernel-source-commit":"e06e6b8001233241eb5b2e2791162f0585f50f4b","syzkaller-git":"https://github.com/google/syzkaller/commits/351cb5cf1aae9dba0fe20d76bd03ff67aaf96a2e","syzkaller-commit":"351cb5cf1aae9dba0fe20d76bd03ff67aaf96a2e","crash-report-link":"/text?tag=CrashReport\u0026x=13f0c8da580000"},{"title":"inconsistent lock state in bpf_lru_push_free","kernel-config":"/text?tag=KernelConfig\u0026x=779072223d02a312","kernel-source-git":"git://git.kernel.org/pub/scm/linux/kernel/git/bpf/bpf.git","kernel-source-commit":"e06e6b8001233241eb5b2e2791162f0585f50f4b","syzkaller-git":"https://github.com/google/syzkaller/commits/2f7f359d8a4db30d79a33f1bbc17a331b1eb58dd","syzkaller-commit":"2f7f359d8a4db30d79a33f1bbc17a331b1eb58dd","crash-report-link":"/text?tag=CrashReport\u0026x=11c01f5a580000"},{"title":"inconsistent lock state in bpf_lru_push_free","kernel-config":"/text?tag=KernelConfig\u0026x=779072223d02a312","kernel-source-git":"git://git.kernel.org/pub/scm/linux/kernel/git/bpf/bpf.git","kernel-source-commit":"e06e6b8001233241eb5b2e2791162f0585f50f4b","syzkaller-git":"https://github.com/google/syzkaller/commits/4efadf07e47be0da3a84005eaac2d3d3ba8eb587","syzkaller-commit":"4efadf07e47be0da3a84005eaac2d3d3ba8eb587","crash-report-link":"/text?tag=CrashReport\u0026x=1335ef5a580000"},{"title":"inconsistent lock state in bpf_lru_push_free","kernel-config":"/text?tag=KernelConfig\u0026x=779072223d02a312","kernel-source-git":"git://git.kernel.org/pub/scm/linux/kernel/git/bpf/bpf.git","kernel-source-commit":"ac72464b10d5975639dedaccf0c372ef670f6abc","syzkaller-git":"https://github.com/google/syzkaller/commits/86914af9098a80da53c3c5d46be980c572ee29f8","syzkaller-commit":"86914af9098a80da53c3c5d46be980c572ee29f8","crash-report-link":"/text?tag=CrashReport\u0026x=140204d6580000"},{"title":"inconsistent lock state in bpf_lru_push_free","kernel-config":"/text?tag=KernelConfig\u0026x=779072223d02a312","kernel-source-git":"git://git.kernel.org/pub/scm/linux/kernel/git/bpf/bpf.git","kernel-source-commit":"ac72464b10d5975639dedaccf0c372ef670f6abc","syzkaller-git":"https://github.com/google/syzkaller/commits/86914af9098a80da53c3c5d46be980c572ee29f8","syzkaller-commit":"86914af9098a80da53c3c5d46be980c572ee29f8","crash-report-link":"/text?tag=CrashReport\u0026x=17e43016580000"},{"title":"inconsistent lock state in bpf_lru_push_free","kernel-config":"/text?tag=KernelConfig\u0026x=779072223d02a312","kernel-source-git":"git://git.kernel.org/pub/scm/linux/kernel/git/bpf/bpf.git","kernel-source-commit":"1f318b96cc84d7c2ab792fcc0bfd42a7ca890681","syzkaller-git":"https://github.com/google/syzkaller/commits/4683d5766812adcf8561dbb9a62b7503165a45a6","syzkaller-commit":"4683d5766812adcf8561dbb9a62b7503165a45a6","crash-report-link":"/text?tag=CrashReport\u0026x=15af53aa580000"},{"title":"inconsistent lock state in bpf_lru_push_free","kernel-config":"/text?tag=KernelConfig\u0026x=779072223d02a312","kernel-source-git":"git://git.kernel.org/pub/scm/linux/kernel/git/bpf/bpf.git","kernel-source-commit":"1f318b96cc84d7c2ab792fcc0bfd42a7ca890681","syzkaller-git":"https://github.com/google/syzkaller/commits/6972f30219093b03bcc1a54487e12a7097245c01","syzkaller-commit":"6972f30219093b03bcc1a54487e12a7097245c01","crash-report-link":"/text?tag=CrashReport\u0026x=15846f5a580000"},{"title":"inconsistent lock state in bpf_lru_push_free","kernel-config":"/text?tag=KernelConfig\u0026x=779072223d02a312","kernel-source-git":"git://git.kernel.org/pub/scm/linux/kernel/git/bpf/bpf.git","kernel-source-commit":"1f318b96cc84d7c2ab792fcc0bfd42a7ca890681","syzkaller-git":"https://github.com/google/syzkaller/commits/6972f30219093b03bcc1a54487e12a7097245c01","syzkaller-commit":"6972f30219093b03bcc1a54487e12a7097245c01","crash-report-link":"/text?tag=CrashReport\u0026x=17b8a8ba580000"},{"title":"inconsistent lock state in bpf_lru_push_free","kernel-config":"/text?tag=KernelConfig\u0026x=779072223d02a312","kernel-source-git":"git://git.kernel.org/pub/scm/linux/kernel/git/bpf/bpf.git","kernel-source-commit":"1f318b96cc84d7c2ab792fcc0bfd42a7ca890681","syzkaller-git":"https://github.com/google/syzkaller/commits/176bead5023749b301d573375d79dabee4d0d888","syzkaller-commit":"176bead5023749b301d573375d79dabee4d0d888","crash-report-link":"/text?tag=CrashReport\u0026x=11cc6a02580000"},{"title":"inconsistent lock state in bpf_lru_push_free","kernel-config":"/text?tag=KernelConfig\u0026x=779072223d02a312","kernel-source-git":"git://git.kernel.org/pub/scm/linux/kernel/git/bpf/bpf.git","kernel-source-commit":"014441d1e4b2f5be728433b761df3377dee7a487","syzkaller-git":"https://github.com/google/syzkaller/commits/5cb44a80412f4dcfba9693d7d0e4c2ae352acdaa","syzkaller-commit":"5cb44a80412f4dcfba9693d7d0e4c2ae352acdaa","crash-report-link":"/text?tag=CrashReport\u0026x=167d03aa580000"},{"title":"inconsistent lock state in bpf_lru_push_free","kernel-config":"/text?tag=KernelConfig\u0026x=779072223d02a312","kernel-source-git":"git://git.kernel.org/pub/scm/linux/kernel/git/bpf/bpf.git","kernel-source-commit":"014441d1e4b2f5be728433b761df3377dee7a487","syzkaller-git":"https://github.com/google/syzkaller/commits/5cb44a80412f4dcfba9693d7d0e4c2ae352acdaa","syzkaller-commit":"5cb44a80412f4dcfba9693d7d0e4c2ae352acdaa","crash-report-link":"/text?tag=CrashReport\u0026x=17f503aa580000"},{"title":"inconsistent lock state in bpf_lru_push_free","kernel-config":"/text?tag=KernelConfig\u0026x=779072223d02a312","kernel-source-git":"git://git.kernel.org/pub/scm/linux/kernel/git/bpf/bpf.git","kernel-source-commit":"014441d1e4b2f5be728433b761df3377dee7a487","syzkaller-git":"https://github.com/google/syzkaller/commits/5cb44a80412f4dcfba9693d7d0e4c2ae352acdaa","syzkaller-commit":"5cb44a80412f4dcfba9693d7d0e4c2ae352acdaa","crash-report-link":"/text?tag=CrashReport\u0026x=134daa02580000"},{"title":"inconsistent lock state in bpf_lru_push_free","kernel-config":"/text?tag=KernelConfig\u0026x=779072223d02a312","kernel-source-git":"git://git.kernel.org/pub/scm/linux/kernel/git/bpf/bpf.git","kernel-source-commit":"1954c4f012206147c34acda8da04f827aa7d3ee3","syzkaller-git":"https://github.com/google/syzkaller/commits/5cb44a80412f4dcfba9693d7d0e4c2ae352acdaa","syzkaller-commit":"5cb44a80412f4dcfba9693d7d0e4c2ae352acdaa","crash-report-link":"/text?tag=CrashReport\u0026x=10042a02580000"},{"title":"inconsistent lock state in bpf_lru_push_free","kernel-config":"/text?tag=KernelConfig\u0026x=779072223d02a312","kernel-source-git":"git://git.kernel.org/pub/scm/linux/kernel/git/bpf/bpf-next.git","kernel-source-commit":"4b21ea5024830f5db6826542048541fab757085b","syzkaller-git":"https://github.com/google/syzkaller/commits/2f245add401a782f9ebb5b5f8dc3e11fe37bf5a9","syzkaller-commit":"2f245add401a782f9ebb5b5f8dc3e11fe37bf5a9","crash-report-link":"/text?tag=CrashReport\u0026x=143e606a580000"},{"title":"inconsistent lock state in bpf_lru_push_free","kernel-config":"/text?tag=KernelConfig\u0026x=779072223d02a312","kernel-source-git":"git://git.kernel.org/pub/scm/linux/kernel/git/bpf/bpf-next.git","kernel-source-commit":"4b21ea5024830f5db6826542048541fab757085b","syzkaller-git":"https://github.com/google/syzkaller/commits/2f245add401a782f9ebb5b5f8dc3e11fe37bf5a9","syzkaller-commit":"2f245add401a782f9ebb5b5f8dc3e11fe37bf5a9","crash-report-link":"/text?tag=CrashReport\u0026x=14befed6580000"},{"title":"inconsistent lock state in bpf_lru_push_free","kernel-config":"/text?tag=KernelConfig\u0026x=779072223d02a312","kernel-source-git":"git://git.kernel.org/pub/scm/linux/kernel/git/bpf/bpf-next.git","kernel-source-commit":"888329ba6c8baa7908e08561c6e89d3fc5680131","syzkaller-git":"https://github.com/google/syzkaller/commits/bd6dcb30873a835583692eaa69f3bafebcba1cfd","syzkaller-commit":"bd6dcb30873a835583692eaa69f3bafebcba1cfd","crash-report-link":"/text?tag=CrashReport\u0026x=1104ded6580000"},{"title":"inconsistent lock state in bpf_lru_push_free","kernel-config":"/text?tag=KernelConfig\u0026x=779072223d02a312","kernel-source-git":"git://git.kernel.org/pub/scm/linux/kernel/git/bpf/bpf-next.git","kernel-source-commit":"888329ba6c8baa7908e08561c6e89d3fc5680131","syzkaller-git":"https://github.com/google/syzkaller/commits/0199f9a13cef46cb5197b1be05347de27bd3bc10","syzkaller-commit":"0199f9a13cef46cb5197b1be05347de27bd3bc10","crash-report-link":"/text?tag=CrashReport\u0026x=14901e02580000"},{"title":"inconsistent lock state in bpf_lru_push_free","kernel-config":"/text?tag=KernelConfig\u0026x=779072223d02a312","kernel-source-git":"git://git.kernel.org/pub/scm/linux/kernel/git/bpf/bpf-next.git","kernel-source-commit":"77378dabb50f593c756d393d8eacb0b91b758863","syzkaller-git":"https://github.com/google/syzkaller/commits/c88105488a5620be13a34f467b1b811950c61bdd","syzkaller-commit":"c88105488a5620be13a34f467b1b811950c61bdd","crash-report-link":"/text?tag=CrashReport\u0026x=11f9e2d6580000"},{"title":"inconsistent lock state in bpf_lru_push_free","kernel-config":"/text?tag=KernelConfig\u0026x=779072223d02a312","kernel-source-git":"git://git.kernel.org/pub/scm/linux/kernel/git/bpf/bpf-next.git","kernel-source-commit":"2364959abecb052d7b798ae51d0626edec8b9288","syzkaller-git":"https://github.com/google/syzkaller/commits/c88105488a5620be13a34f467b1b811950c61bdd","syzkaller-commit":"c88105488a5620be13a34f467b1b811950c61bdd","crash-report-link":"/text?tag=CrashReport\u0026x=1453006a580000"},{"title":"inconsistent lock state in bpf_lru_push_free","kernel-config":"/text?tag=KernelConfig\u0026x=779072223d02a312","kernel-source-git":"git://git.kernel.org/pub/scm/linux/kernel/git/bpf/bpf-next.git","kernel-source-commit":"2364959abecb052d7b798ae51d0626edec8b9288","syzkaller-git":"https://github.com/google/syzkaller/commits/c01bca7439117559131c7afa36f261a369581611","syzkaller-commit":"c01bca7439117559131c7afa36f261a369581611","crash-report-link":"/text?tag=CrashReport\u0026x=14c6b406580000"},{"title":"inconsistent lock state in bpf_lru_push_free","kernel-config":"/text?tag=KernelConfig\u0026x=779072223d02a312","kernel-source-git":"git://git.kernel.org/pub/scm/linux/kernel/git/bpf/bpf-next.git","kernel-source-commit":"bb41fcef5c7932e61ce87f573497ab0472cfe496","syzkaller-git":"https://github.com/google/syzkaller/commits/ee8d34d6bd63c940254cb452fca7cb4fdfe419e8","syzkaller-commit":"ee8d34d6bd63c940254cb452fca7cb4fdfe419e8","crash-report-link":"/text?tag=CrashReport\u0026x=10885602580000"},{"title":"inconsistent lock state in bpf_lru_push_free","kernel-config":"/text?tag=KernelConfig\u0026x=779072223d02a312","kernel-source-git":"git://git.kernel.org/pub/scm/linux/kernel/git/bpf/bpf-next.git","kernel-source-commit":"bb41fcef5c7932e61ce87f573497ab0472cfe496","syzkaller-git":"https://github.com/google/syzkaller/commits/ee8d34d6bd63c940254cb452fca7cb4fdfe419e8","syzkaller-commit":"ee8d34d6bd63c940254cb452fca7cb4fdfe419e8","crash-report-link":"/text?tag=CrashReport\u0026x=171f9602580000"},{"title":"inconsistent lock state in bpf_lru_push_free","kernel-config":"/text?tag=KernelConfig\u0026x=779072223d02a312","kernel-source-git":"git://git.kernel.org/pub/scm/linux/kernel/git/bpf/bpf-next.git","kernel-source-commit":"ca0f39a369c5f927c3d004e63a5a778b08a9df94","syzkaller-git":"https://github.com/google/syzkaller/commits/4efadf07e47be0da3a84005eaac2d3d3ba8eb587","syzkaller-commit":"4efadf07e47be0da3a84005eaac2d3d3ba8eb587","crash-report-link":"/text?tag=CrashReport\u0026x=1411775a580000"},{"title":"inconsistent lock state in bpf_lru_push_free","kernel-config":"/text?tag=KernelConfig\u0026x=779072223d02a312","kernel-source-git":"git://git.kernel.org/pub/scm/linux/kernel/git/bpf/bpf-next.git","kernel-source-commit":"e95e85b8914be1c951a1ead34b1353592719e26e","syzkaller-git":"https://github.com/google/syzkaller/commits/2d88ab014d9ef9a6133ad5a5851bb4fd42959ad3","syzkaller-commit":"2d88ab014d9ef9a6133ad5a5851bb4fd42959ad3","crash-report-link":"/text?tag=CrashReport\u0026x=138d575a580000"},{"title":"inconsistent lock state in bpf_lru_push_free","kernel-config":"/text?tag=KernelConfig\u0026x=779072223d02a312","kernel-source-git":"git://git.kernel.org/pub/scm/linux/kernel/git/bpf/bpf-next.git","kernel-source-commit":"e95e85b8914be1c951a1ead34b1353592719e26e","syzkaller-git":"https://github.com/google/syzkaller/commits/2d88ab014d9ef9a6133ad5a5851bb4fd42959ad3","syzkaller-commit":"2d88ab014d9ef9a6133ad5a5851bb4fd42959ad3","crash-report-link":"/text?tag=CrashReport\u0026x=1321575a580000"},{"title":"inconsistent lock state in bpf_lru_push_free","kernel-config":"/text?tag=KernelConfig\u0026x=779072223d02a312","kernel-source-git":"git://git.kernel.org/pub/scm/linux/kernel/git/bpf/bpf-next.git","kernel-source-commit":"0c55d4817aff454cfaded4f161ab13f2049758a9","syzkaller-git":"https://github.com/google/syzkaller/commits/86914af9098a80da53c3c5d46be980c572ee29f8","syzkaller-commit":"86914af9098a80da53c3c5d46be980c572ee29f8","crash-report-link":"/text?tag=CrashReport\u0026x=128e04d6580000"},{"title":"inconsistent lock state in bpf_lru_push_free","kernel-config":"/text?tag=KernelConfig\u0026x=779072223d02a312","kernel-source-git":"git://git.kernel.org/pub/scm/linux/kernel/git/bpf/bpf-next.git","kernel-source-commit":"bd2e02e3c9215305dfa344c050d5822f19929cf7","syzkaller-git":"https://github.com/google/syzkaller/commits/176bead5023749b301d573375d79dabee4d0d888","syzkaller-commit":"176bead5023749b301d573375d79dabee4d0d888","crash-report-link":"/text?tag=CrashReport\u0026x=1269e806580000"},{"title":"inconsistent lock state in bpf_lru_push_free","kernel-config":"/text?tag=KernelConfig\u0026x=779072223d02a312","kernel-source-git":"git://git.kernel.org/pub/scm/linux/kernel/git/bpf/bpf-next.git","kernel-source-commit":"099bded7525d9803f62bc5a1ed60e2c9ec4851e0","syzkaller-git":"https://github.com/google/syzkaller/commits/5cb44a80412f4dcfba9693d7d0e4c2ae352acdaa","syzkaller-commit":"5cb44a80412f4dcfba9693d7d0e4c2ae352acdaa","crash-report-link":"/text?tag=CrashReport\u0026x=146d78d6580000"},{"title":"inconsistent lock state in bpf_lru_push_free","kernel-config":"/text?tag=KernelConfig\u0026x=93740e6c6567fcec","kernel-source-git":"git://git.kernel.org/pub/scm/linux/kernel/git/bpf/bpf-next.git","kernel-source-commit":"6dd780f973816133f189efec04118c1e6b1b443d","syzkaller-git":"https://github.com/google/syzkaller/commits/5cb44a80412f4dcfba9693d7d0e4c2ae352acdaa","syzkaller-commit":"5cb44a80412f4dcfba9693d7d0e4c2ae352acdaa","crash-report-link":"/text?tag=CrashReport\u0026x=16aa78d6580000"},{"title":"inconsistent lock state in bpf_lru_push_free","kernel-config":"/text?tag=KernelConfig\u0026x=93740e6c6567fcec","kernel-source-git":"git://git.kernel.org/pub/scm/linux/kernel/git/bpf/bpf-next.git","kernel-source-commit":"6dd780f973816133f189efec04118c1e6b1b443d","syzkaller-git":"https://github.com/google/syzkaller/commits/5cb44a80412f4dcfba9693d7d0e4c2ae352acdaa","syzkaller-commit":"5cb44a80412f4dcfba9693d7d0e4c2ae352acdaa","crash-report-link":"/text?tag=CrashReport\u0026x=135f3fe6580000"}]}