{"version":1,"title":"KCSAN: data-race in fill_mg_cmtime / inode_set_ctime_to_ts","id":"011e182ed50f8c5bc0a2da8c15cc85cac46e5e96","status":"upstream: reported on 2026/05/16 22:06","first-crash":"2026-05-16T21:14:56.852632Z","last-crash":"2026-05-16T21:14:56.896029Z","discussions":["https://groups.google.com/d/msgid/syzkaller-bugs/6a08ea68.170a0220.1ad1c0.000f.GAE@google.com"],"crashes":[{"title":"KCSAN: data-race in fill_mg_cmtime / inode_set_ctime_to_ts","kernel-config":"/text?tag=KernelConfig\u0026x=2e40c0f41e01837e","kernel-source-git":"git://git.kernel.org/pub/scm/linux/kernel/git/torvalds/linux.git","kernel-source-commit":"6916d5703ddf9a38f1f6c2cc793381a24ee914c6","syzkaller-git":"https://github.com/google/syzkaller/commits/de5aae85e5f28e2fa1c7deefcc24fe286abe5140","syzkaller-commit":"de5aae85e5f28e2fa1c7deefcc24fe286abe5140","crash-report-link":"/text?tag=CrashReport\u0026x=10393f6c580000"}]}